odoo/addons/res_project/README.rst
odoo/addons/res_project/__init__.py
odoo/addons/res_project/__manifest__.py
odoo/addons/res_project/hooks.py
odoo/addons/res_project/data/res_project_cron.xml
odoo/addons/res_project/data/res_project_data.xml
odoo/addons/res_project/models/__init__.py
odoo/addons/res_project/models/hr_department.py
odoo/addons/res_project/models/hr_employee_base.py
odoo/addons/res_project/models/res_project.py
odoo/addons/res_project/models/res_project_plan.py
odoo/addons/res_project/readme/CONFIGURE.md
odoo/addons/res_project/readme/CONTRIBUTORS.md
odoo/addons/res_project/readme/DESCRIPTION.md
odoo/addons/res_project/security/ir.model.access.csv
odoo/addons/res_project/security/res_project_security_groups.xml
odoo/addons/res_project/static/description/icon.png
odoo/addons/res_project/static/description/index.html
odoo/addons/res_project/tests/__init__.py
odoo/addons/res_project/tests/common.py
odoo/addons/res_project/tests/test_res_project.py
odoo/addons/res_project/views/hr_department_views.xml
odoo/addons/res_project/views/hr_employee_views.xml
odoo/addons/res_project/views/res_project_menuitem.xml
odoo/addons/res_project/views/res_project_split.xml
odoo/addons/res_project/views/res_project_views.xml
odoo/addons/res_project/wizard/__init__.py
odoo/addons/res_project/wizard/split_project_wizard.py
odoo/addons/res_project/wizard/split_project_wizard_view.xml
odoo_addon_res_project-18.0.1.0.1.dist-info/METADATA
odoo_addon_res_project-18.0.1.0.1.dist-info/WHEEL
odoo_addon_res_project-18.0.1.0.1.dist-info/top_level.txt
odoo_addon_res_project-18.0.1.0.1.dist-info/RECORD
